Sympy111Documentation/README.md
Sympy111Documentation/__init__.py
Sympy111Documentation/__main__.py
Sympy111Documentation/file.epub
Sympy111Documentation/index.html
Sympy111Documentation/css/__init__.py
Sympy111Documentation/css/annotations.css
Sympy111Documentation/css/main.css
Sympy111Documentation/css/normalize.css
Sympy111Documentation/css/popup.css
Sympy111Documentation/font/__init__.py
Sympy111Documentation/font/fontello.eot
Sympy111Documentation/font/fontello.svg
Sympy111Documentation/font/fontello.ttf
Sympy111Documentation/font/fontello.woff
Sympy111Documentation/img/__init__.py
Sympy111Documentation/img/annotator-glyph-sprite.png
Sympy111Documentation/img/annotator-icon-sprite.png
Sympy111Documentation/img/apple-touch-icon.png
Sympy111Documentation/img/cancelfullscreen.png
Sympy111Documentation/img/close.png
Sympy111Documentation/img/fullscreen.png
Sympy111Documentation/img/loader.gif
Sympy111Documentation/img/menu-icon.png
Sympy111Documentation/img/save.png
Sympy111Documentation/img/saved.png
Sympy111Documentation/img/settings-s.png
Sympy111Documentation/img/settings.png
Sympy111Documentation/img/star.png
Sympy111Documentation/js/__init__.py
Sympy111Documentation/js/epub.js
Sympy111Documentation/js/epub.min.js
Sympy111Documentation/js/epub.min.map
Sympy111Documentation/js/hooks.min.js
Sympy111Documentation/js/hooks.min.map
Sympy111Documentation/js/reader.js
Sympy111Documentation/js/reader.js.map
Sympy111Documentation/js/reader.min.js
Sympy111Documentation/js/reader.min.map
Sympy111Documentation/js/hooks/__init__.py
Sympy111Documentation/js/hooks/extensions/__init__.py
Sympy111Documentation/js/hooks/extensions/highlight.js
Sympy111Documentation/js/libs/__init__.py
Sympy111Documentation/js/libs/jquery.min.js
Sympy111Documentation/js/libs/localforage.min.js
Sympy111Documentation/js/libs/screenfull.js
Sympy111Documentation/js/libs/screenfull.min.js
Sympy111Documentation/js/libs/zip.min.js
Sympy111Documentation/js/plugins/__init__.py
sympy_1_1_1_documentation-2024.3.2.0.dist-info/METADATA
sympy_1_1_1_documentation-2024.3.2.0.dist-info/WHEEL
sympy_1_1_1_documentation-2024.3.2.0.dist-info/entry_points.txt
sympy_1_1_1_documentation-2024.3.2.0.dist-info/top_level.txt
sympy_1_1_1_documentation-2024.3.2.0.dist-info/RECORD
